sequence_unet/__init__.py
sequence_unet/graph_cnn.py
sequence_unet/metrics.py
sequence_unet/models.py
sequence_unet/predict.py
sequence_unet/scripts/__init__.py
sequence_unet/scripts/filter_fasta.py
sequence_unet/scripts/make_preds.py
sequence_unet/scripts/split_fasta.py
sequence_unet-1.0.3.dist-info/LICENCE.md
sequence_unet-1.0.3.dist-info/METADATA
sequence_unet-1.0.3.dist-info/WHEEL
sequence_unet-1.0.3.dist-info/entry_points.txt
sequence_unet-1.0.3.dist-info/top_level.txt
sequence_unet-1.0.3.dist-info/zip-safe
sequence_unet-1.0.3.dist-info/RECORD
