Metadata-Version: 2.1
Name: sequence-unet
Version: 1.0.3
Summary: Make protein predictions with Sequence UNET and train new models
Author: Pedro Beltrao, Mohammed AlQuraishi
Author-email: Alistair Dunham <ad44@sanger.ac.uk>
Maintainer-email: Alistair Dunham <ad44@sanger.ac.uk>
Project-URL: Repository, https://github.com/allydunham/sequence_unet
Project-URL: Documentation, https://sequence-unet.readthedocs.io/en/latest/
Project-URL: Publication, https://doi.org/10.1186/s13059-023-02948-3
Keywords: deep learning,neural network,protein,bioinformatics,variant effect prediction
Requires-Python: >=3.6
License-File: LICENCE.md
Requires-Dist: numpy
Requires-Dist: pandas
Requires-Dist: biopython
Requires-Dist: tqdm
Requires-Dist: proteinnetpy
Requires-Dist: tensorflow (<3.0.0,>=2.6.0) ; sys_platform != "darwin" or platform_machine != "arm64"
Requires-Dist: tensorflow-macos (<3.0.0,>=2.6.0) ; sys_platform == "darwin" and platform_machine == "arm64"
